{"meta":{"linha":"109","dia_semana":"","data_execucao":"2026-06-23","titulo":"TABELA HORÁRIA","subtitulo":"","tipo":"uteis"},"colunas":[{"chave":"col_1","rotulo":"Coluna 1","largura":56,"alinhamento":"centro"},{"chave":"cheg","rotulo":"Cheg.","largura":69,"alinhamento":"centro"},{"chave":"saida","rotulo":"Saída","largura":69,"alinhamento":"centro"},{"chave":"col_4","rotulo":"Coluna 4","largura":56,"alinhamento":"centro"},{"chave":"col_5","rotulo":"|","largura":56,"alinhamento":"centro"},{"chave":"cheg","rotulo":"Cheg.","largura":69,"alinhamento":"centro"},{"chave":"saida","rotulo":"Saída","largura":69,"alinhamento":"centro"},{"chave":"col_8","rotulo":"Coluna 8","largura":56,"alinhamento":"centro"},{"chave":"col_9","rotulo":"Coluna 9","largura":56,"alinhamento":"centro"},{"chave":"col_10","rotulo":"Coluna 10","largura":56,"alinhamento":"centro"}],"linhas":[{"col_1":"","cheg":"--:--","saida":"--:--","col_4":"--:--","col_5":"|","col_8":"--:--","col_9":"","col_10":""},{"col_1":"","cheg":"--:--","saida":"05:45","col_4":"05:37","col_5":"|","col_8":"05:52","col_9":"","col_10":""},{"col_1":"","cheg":"06:10","saida":"06:15","col_4":"06:07","col_5":"|","col_8":"06:22","col_9":"","col_10":""},{"col_1":"","cheg":"06:40","saida":"06:45","col_4":"06:37","col_5":"|","col_8":"06:52","col_9":"","col_10":""},{"col_1":"","cheg":"07:10","saida":"07:15","col_4":"07:07","col_5":"|","col_8":"07:22","col_9":"","col_10":""},{"col_1":"","cheg":"07:40","saida":"07:45","col_4":"07:37","col_5":"|","col_8":"07:52","col_9":"","col_10":""},{"col_1":"","cheg":"08:10","saida":"08:15","col_4":"08:07","col_5":"|","col_8":"08:22","col_9":"","col_10":""},{"col_1":"","cheg":"08:40","saida":"08:45","col_4":"08:37","col_5":"|","col_8":"08:52","col_9":"","col_10":""},{"col_1":"","cheg":"09:10","saida":"09:15","col_4":"09:07","col_5":"|","col_8":"09:22","col_9":"","col_10":""},{"col_1":"","cheg":"09:40","saida":"09:45","col_4":"09:37","col_5":"|","col_8":"09:52","col_9":"","col_10":""},{"col_1":"","cheg":"10:10","saida":"10:15","col_4":"10:07","col_5":"|","col_8":"10:22","col_9":"","col_10":""},{"col_1":"","cheg":"10:40","saida":"10:45","col_4":"10:37","col_5":"|","col_8":"10:52","col_9":"","col_10":""},{"col_1":"","cheg":"11:10","saida":"11:15","col_4":"11:07","col_5":"|","col_8":"11:22","col_9":"","col_10":""},{"col_1":"","cheg":"11:40","saida":"11:45","col_4":"11:37","col_5":"|","col_8":"11:52","col_9":"","col_10":""},{"col_1":"","cheg":"12:10","saida":"12:15","col_4":"12:07","col_5":"|","col_8":"12:22","col_9":"","col_10":""},{"col_1":"","cheg":"12:40","saida":"12:45","col_4":"12:37","col_5":"|","col_8":"12:52","col_9":"","col_10":""},{"col_1":"","cheg":"13:10","saida":"13:15","col_4":"13:07","col_5":"|","col_8":"13:22","col_9":"","col_10":""},{"col_1":"","cheg":"13:40","saida":"13:45","col_4":"13:37","col_5":"|","col_8":"13:52","col_9":"","col_10":""},{"col_1":"","cheg":"14:10","saida":"14:15","col_4":"14:07","col_5":"|","col_8":"14:22","col_9":"","col_10":""},{"col_1":"","cheg":"14:40","saida":"14:45","col_4":"14:37","col_5":"|","col_8":"14:52","col_9":"","col_10":""},{"col_1":"","cheg":"15:10","saida":"15:15","col_4":"15:07","col_5":"|","col_8":"15:22","col_9":"","col_10":""},{"col_1":"","cheg":"15:40","saida":"15:45","col_4":"15:37","col_5":"|","col_8":"15:52","col_9":"","col_10":""},{"col_1":"","cheg":"16:10","saida":"16:15","col_4":"16:07","col_5":"|","col_8":"16:25","col_9":"","col_10":""},{"col_1":"","cheg":"16:45","saida":"16:50","col_4":"16:45","col_5":"|","col_8":"17:00","col_9":"","col_10":""},{"col_1":"","cheg":"17:20","saida":"17:25","col_4":"17:20","col_5":"|","col_8":"17:35","col_9":"","col_10":""},{"col_1":"","cheg":"17:55","saida":"18:00","col_4":"17:55","col_5":"|","col_8":"18:10","col_9":"","col_10":""},{"col_1":"","cheg":"18:30","saida":"18:35","col_4":"18:30","col_5":"|","col_8":"18:45","col_9":"","col_10":""},{"col_1":"","cheg":"19:05","saida":"19:10","col_4":"19:05","col_5":"|","col_8":"19:17","col_9":"","col_10":""},{"col_1":"","cheg":"19:38","saida":"19:43","col_4":"19:37","col_5":"|","col_8":"19:50","col_9":"","col_10":""},{"col_1":"","cheg":"20:04","saida":"20:09","col_4":"20:03","col_5":"|","col_8":"20:16","col_9":"","col_10":""},{"col_1":"","cheg":"20:30","saida":"20:35","col_4":"20:29","col_5":"|","col_8":"20:42","col_9":"","col_10":""},{"col_1":"","cheg":"20:56","saida":"21:01","col_4":"20:55","col_5":"|","col_8":"21:08","col_9":"","col_10":""},{"col_1":"","cheg":"21:22","saida":"21:27","col_4":"21:21","col_5":"|","col_8":"21:34","col_9":"","col_10":""},{"col_1":"","cheg":"21:48","saida":"21:53","col_4":"21:47","col_5":"|","col_8":"22:00","col_9":"","col_10":""},{"col_1":"","cheg":"22:14","saida":"22:19","col_4":"22:13","col_5":"|","col_8":"22:26","col_9":"","col_10":""},{"col_1":"","cheg":"22:40","saida":"22:45","col_4":"22:39","col_5":"|","col_8":"22:52","col_9":"","col_10":""},{"col_1":"","cheg":"23:06","saida":"23:11","col_4":"23:05","col_5":"|","col_8":"23:18","col_9":"","col_10":""},{"col_1":"","cheg":"23:32","saida":"23:37","col_4":"--:--","col_5":"|","col_8":"23:44","col_9":"","col_10":""},{"col_1":"","cheg":"23:58","saida":"00:03","col_4":"--:--","col_5":"|","col_8":"00:10","col_9":"","col_10":""},{"col_1":"","cheg":"00:24","saida":"00:29","col_4":"--:--","col_5":"|","col_8":"--:--","col_9":"","col_10":""},{"col_1":"","cheg":"--:--","saida":"Rec.","col_4":"--:--","col_5":"|","col_8":"--:--","col_9":"","col_10":""},{"col_1":"","cheg":"--:--","saida":"--:--","col_4":"--:--","col_5":"|","col_8":"--:--","col_9":"","col_10":""},{"col_1":"","cheg":"Via Leste-Oeste","saida":"","col_4":"","col_5":"|","col_8":"","col_9":"","col_10":""},{"col_1":"","cheg":"18:44","saida":"","col_4":"","col_5":"","col_8":"","col_9":"","col_10":""}],"id":"109-uteis"}