{"meta":{"linha":"420","dia_semana":"","data_execucao":"2026-06-23","titulo":"TABELA HORÁRIA","subtitulo":"","tipo":"uteis"},"colunas":[{"chave":"col_1","rotulo":"Coluna 1","largura":56,"alinhamento":"centro"},{"chave":"cheg","rotulo":"Cheg.","largura":69,"alinhamento":"centro"},{"chave":"saida","rotulo":"Saída","largura":69,"alinhamento":"centro"},{"chave":"col_4","rotulo":"Coluna 4","largura":56,"alinhamento":"centro"},{"chave":"col_5","rotulo":"Coluna 5","largura":56,"alinhamento":"centro"},{"chave":"col_6","rotulo":"Coluna 6","largura":56,"alinhamento":"centro"},{"chave":"col_7","rotulo":"|","largura":56,"alinhamento":"centro"},{"chave":"cheg","rotulo":"Cheg.","largura":69,"alinhamento":"centro"},{"chave":"saida","rotulo":"Saída","largura":69,"alinhamento":"centro"},{"chave":"col_10","rotulo":"Coluna 10","largura":56,"alinhamento":"centro"},{"chave":"col_11","rotulo":"Coluna 11","largura":56,"alinhamento":"centro"},{"chave":"col_12","rotulo":"Coluna 12","largura":56,"alinhamento":"centro"},{"chave":"col_13","rotulo":"|","largura":56,"alinhamento":"centro"},{"chave":"cheg","rotulo":"Cheg.","largura":69,"alinhamento":"centro"},{"chave":"saida","rotulo":"Saída","largura":69,"alinhamento":"centro"},{"chave":"col_16","rotulo":"Coluna 16","largura":56,"alinhamento":"centro"},{"chave":"col_17","rotulo":"Coluna 17","largura":56,"alinhamento":"centro"},{"chave":"col_18","rotulo":"Coluna 18","largura":56,"alinhamento":"centro"},{"chave":"col_19","rotulo":"|","largura":56,"alinhamento":"centro"},{"chave":"cheg","rotulo":"Cheg.","largura":69,"alinhamento":"centro"},{"chave":"saida","rotulo":"Saída","largura":69,"alinhamento":"centro"},{"chave":"col_22","rotulo":"Coluna 22","largura":56,"alinhamento":"centro"},{"chave":"col_23","rotulo":"Coluna 23","largura":56,"alinhamento":"centro"},{"chave":"col_24","rotulo":"Coluna 24","largura":56,"alinhamento":"centro"},{"chave":"col_25","rotulo":"|","largura":56,"alinhamento":"centro"},{"chave":"cheg","rotulo":"Cheg.","largura":69,"alinhamento":"centro"},{"chave":"saida","rotulo":"Saída","largura":69,"alinhamento":"centro"},{"chave":"col_28","rotulo":"Coluna 28","largura":56,"alinhamento":"centro"},{"chave":"col_29","rotulo":"Coluna 29","largura":56,"alinhamento":"centro"},{"chave":"col_30","rotulo":"Coluna 30","largura":56,"alinhamento":"centro"},{"chave":"col_31","rotulo":"Coluna 31","largura":56,"alinhamento":"centro"},{"chave":"col_32","rotulo":"Coluna 32","largura":56,"alinhamento":"centro"},{"chave":"col_33","rotulo":"Coluna 33","largura":56,"alinhamento":"centro"},{"chave":"col_34","rotulo":"Coluna 34","largura":56,"alinhamento":"centro"},{"chave":"col_35","rotulo":"Coluna 35","largura":56,"alinhamento":"centro"},{"chave":"col_36","rotulo":"Coluna 36","largura":56,"alinhamento":"centro"},{"chave":"col_37","rotulo":"Coluna 37","largura":56,"alinhamento":"centro"},{"chave":"col_38","rotulo":"Coluna 38","largura":56,"alinhamento":"centro"}],"linhas":[{"col_1":"","cheg":"Carro do 512 tab. 03","saida":"","col_4":"--:--","col_5":"--:--","col_6":"--:--","col_7":"|","col_10":"--:--","col_11":"--:--","col_12":"--:--","col_13":"|","col_16":"--:--","col_17":"--:--","col_18":"--:--","col_19":"|","col_22":"--:--","col_23":"--:--","col_24":"--:--","col_25":"|","col_28":"","col_29":"","col_30":"","col_31":"","col_32":"","col_33":"","col_34":"","col_35":"","col_36":"","col_37":"","col_38":""},{"col_1":"","cheg":"--:--","saida":"--:--","col_4":"--:--","col_5":"05:15","col_6":"--:--","col_7":"|","col_10":"--:--","col_11":"05:32","col_12":"--:--","col_13":"|","col_16":"--:--","col_17":"05:49","col_18":"--:--","col_19":"|","col_22":"--:--","col_23":"06:06","col_24":"--:--","col_25":"|","col_28":"07:02","col_29":"07:07","col_30":"--:--","col_31":"","col_32":"","col_33":"","col_34":"","col_35":"","col_36":"","col_37":"","col_38":""},{"col_1":"","cheg":"Entra no 800 tab. 08","saida":"","col_4":"05:30","col_5":"--:--","col_6":"--:--","col_7":"|","col_10":"05:47","col_11":"--:--","col_12":"--:--","col_13":"|","col_16":"06:04","col_17":"--:--","col_18":"--:--","col_19":"|","col_22":"06:21","col_23":"--:--","col_24":"--:--","col_25":"|","col_28":"","col_29":"","col_30":"","col_31":"","col_32":"","col_33":"","col_34":"","col_35":"","col_36":"","col_37":"","col_38":""},{"col_1":"","cheg":"--:--","saida":"--:--","col_4":"06:00","col_5":"06:15","col_6":"06:17","col_7":"|","col_10":"06:18","col_11":"06:33","col_12":"06:35","col_13":"|","col_16":"06:35","col_17":"06:50","col_18":"06:52","col_19":"|","col_22":"06:52","col_23":"07:07","col_24":"07:09","col_25":"|","col_28":"--:--","col_29":"--:--","col_30":"--:--","col_31":"","col_32":"","col_33":"","col_34":"","col_35":"","col_36":"","col_37":"","col_38":""},{"col_1":"","cheg":"--:--","saida":"--:--","col_4":"--:--","col_5":"06:22","col_6":"--:--","col_7":"|","col_10":"--:--","col_11":"06:40","col_12":"--:--","col_13":"|","col_16":"--:--","col_17":"06:57","col_18":"--:--","col_19":"|","col_22":"--:--","col_23":"07:14","col_24":"--:--","col_25":"|","col_28":"--:--","col_29":"--:--","col_30":"--:--","col_31":"","col_32":"","col_33":"","col_34":"","col_35":"","col_36":"","col_37":"","col_38":""},{"col_1":"","cheg":"--:--","saida":"--:--","col_4":"06:37","col_5":"--:--","col_6":"--:--","col_7":"|","col_10":"06:55","col_11":"--:--","col_12":"--:--","col_13":"|","col_16":"07:12","col_17":"--:--","col_18":"--:--","col_19":"|","col_22":"07:29","col_23":"--:--","col_24":"--:--","col_25":"|","col_28":"--:--","col_29":"--:--","col_30":"--:--","col_31":"","col_32":"","col_33":"","col_34":"","col_35":"","col_36":"","col_37":"","col_38":""},{"col_1":"","cheg":"--:--","saida":"--:--","col_4":"07:08","col_5":"07:23","col_6":"07:25","col_7":"|","col_10":"07:26","col_11":"07:41","col_12":"07:43","col_13":"|","col_16":"07:43","col_17":"07:58","col_18":"08:00","col_19":"|","col_22":"08:00","col_23":"08:15","col_24":"08:17","col_25":"|","col_28":"--:--","col_29":"--:--","col_30":"--:--","col_31":"","col_32":"","col_33":"","col_34":"","col_35":"","col_36":"","col_37":"","col_38":""},{"col_1":"","cheg":"--:--","saida":"--:--","col_4":"--:--","col_5":"07:30","col_6":"--:--","col_7":"|","col_10":"--:--","col_11":"07:48","col_12":"--:--","col_13":"|","col_16":"--:--","col_17":"08:05","col_18":"--:--","col_19":"|","col_22":"--:--","col_23":"08:22","col_24":"--:--","col_25":"|","col_28":"--:--","col_29":"--:--","col_30":"--:--","col_31":"","col_32":"","col_33":"","col_34":"","col_35":"","col_36":"","col_37":"","col_38":""},{"col_1":"","cheg":"--:--","saida":"--:--","col_4":"07:45","col_5":"--:--","col_6":"--:--","col_7":"|","col_10":"08:03","col_11":"--:--","col_12":"--:--","col_13":"|","col_16":"08:20","col_17":"--:--","col_18":"--:--","col_19":"|","col_22":"08:37","col_23":"--:--","col_24":"--:--","col_25":"|","col_28":"--:--","col_29":"--:--","col_30":"--:--","col_31":"","col_32":"","col_33":"","col_34":"","col_35":"","col_36":"","col_37":"","col_38":""},{"col_1":"","cheg":"T. Vivi Xavier","saida":"","col_4":"08:16","col_5":"08:31","col_6":"08:33","col_7":"|","col_10":"08:34","col_11":"08:49","col_12":"08:51","col_13":"|","col_16":"08:51","col_17":"09:06","col_18":"09:08","col_19":"|","col_22":"09:08","col_23":"09:23","col_24":"09:25","col_25":"|","col_28":"T. O. V.","col_29":"IFPR","col_30":"T. M. G","col_31":"","col_32":"","col_33":"","col_34":"","col_35":"","col_36":"","col_37":"","col_38":""},{"col_1":"","cheg":"Cheg.","saida":"Saída","col_4":"--:--","col_5":"08:38","col_6":"--:--","col_7":"|","col_10":"--:--","col_11":"08:56","col_12":"--:--","col_13":"|","col_16":"--:--","col_17":"09:13","col_18":"--:--","col_19":"|","col_22":"--:--","col_23":"09:30","col_24":"--:--","col_25":"|","col_28":"","col_29":"","col_30":"","col_31":"","col_32":"","col_33":"","col_34":"","col_35":"","col_36":"","col_37":"","col_38":""},{"col_1":"","cheg":"--:--","saida":"--:--","col_4":"08:53","col_5":"--:--","col_6":"--:--","col_7":"|","col_10":"09:11","col_11":"--:--","col_12":"--:--","col_13":"|","col_16":"09:28","col_17":"--:--","col_18":"--:--","col_19":"|","col_22":"09:45","col_23":"--:--","col_24":"--:--","col_25":"|","col_28":"--:--","col_29":"--:--","col_30":"--:--","col_31":"","col_32":"","col_33":"","col_34":"","col_35":"","col_36":"","col_37":"","col_38":""},{"col_1":"","cheg":"--:--","saida":"--:--","col_4":"09:24","col_5":"09:39","col_6":"09:41","col_7":"|","col_10":"09:42","col_11":"09:57","col_12":"09:59","col_13":"|","col_16":"09:59","col_17":"10:14","col_18":"10:16","col_19":"|","col_22":"10:16","col_23":"10:31","col_24":"10:33","col_25":"|","col_28":"12:25","col_29":"12:30","col_30":"--:--","col_31":"","col_32":"","col_33":"","col_34":"","col_35":"","col_36":"","col_37":"","col_38":""},{"col_1":"","cheg":"--:--","saida":"--:--","col_4":"--:--","col_5":"09:46","col_6":"--:--","col_7":"|","col_10":"--:--","col_11":"10:04","col_12":"--:--","col_13":"|","col_16":"--:--","col_17":"10:21","col_18":"--:--","col_19":"|","col_22":"--:--","col_23":"10:38","col_24":"--:--","col_25":"|","col_28":"12:45","col_29":"--:--","col_30":"--:--","col_31":"","col_32":"","col_33":"","col_34":"","col_35":"","col_36":"","col_37":"","col_38":""},{"col_1":"","cheg":"--:--","saida":"--:--","col_4":"10:01","col_5":"--:--","col_6":"--:--","col_7":"|","col_10":"10:19","col_11":"--:--","col_12":"--:--","col_13":"|","col_16":"10:36","col_17":"--:--","col_18":"--:--","col_19":"|","col_22":"10:53","col_23":"--:--","col_24":"--:--","col_25":"|","col_28":"Rec.","col_29":"--:--","col_30":"--:--","col_31":"","col_32":"","col_33":"","col_34":"","col_35":"","col_36":"","col_37":"","col_38":""},{"col_1":"","cheg":"--:--","saida":"--:--","col_4":"10:32","col_5":"10:47","col_6":"10:49","col_7":"|","col_10":"10:50","col_11":"11:05","col_12":"11:07","col_13":"|","col_16":"11:07","col_17":"11:22","col_18":"11:24","col_19":"|","col_22":"11:24","col_23":"11:39","col_24":"11:41","col_25":"|","col_28":"--:--","col_29":"--:--","col_30":"--:--","col_31":"","col_32":"","col_33":"","col_34":"","col_35":"","col_36":"","col_37":"","col_38":""},{"col_1":"","cheg":"--:--","saida":"--:--","col_4":"--:--","col_5":"10:54","col_6":"--:--","col_7":"|","col_10":"--:--","col_11":"11:12","col_12":"--:--","col_13":"|","col_16":"--:--","col_17":"11:29","col_18":"--:--","col_19":"|","col_22":"--:--","col_23":"11:46","col_24":"--:--","col_25":"|","col_28":"--:--","col_29":"--:--","col_30":"--:--","col_31":"","col_32":"","col_33":"","col_34":"","col_35":"","col_36":"","col_37":"","col_38":""},{"col_1":"","cheg":"--:--","saida":"--:--","col_4":"11:09","col_5":"--:--","col_6":"--:--","col_7":"|","col_10":"11:27","col_11":"--:--","col_12":"--:--","col_13":"|","col_16":"11:44","col_17":"--:--","col_18":"--:--","col_19":"|","col_22":"12:01","col_23":"--:--","col_24":"--:--","col_25":"|","col_28":"--:--","col_29":"--:--","col_30":"--:--","col_31":"","col_32":"","col_33":"","col_34":"","col_35":"","col_36":"","col_37":"","col_38":""},{"col_1":"","cheg":"--:--","saida":"--:--","col_4":"11:40","col_5":"11:55","col_6":"11:57","col_7":"|","col_10":"11:58","col_11":"12:13","col_12":"12:15","col_13":"|","col_16":"12:15","col_17":"12:30","col_18":"12:32","col_19":"|","col_22":"12:32","col_23":"12:47","col_24":"12:49","col_25":"|","col_28":"--:--","col_29":"--:--","col_30":"--:--","col_31":"","col_32":"","col_33":"","col_34":"","col_35":"","col_36":"","col_37":"","col_38":""},{"col_1":"","cheg":"--:--","saida":"--:--","col_4":"--:--","col_5":"12:02","col_6":"--:--","col_7":"|","col_10":"--:--","col_11":"12:20","col_12":"--:--","col_13":"|","col_16":"--:--","col_17":"12:37","col_18":"--:--","col_19":"|","col_22":"--:--","col_23":"12:54","col_24":"--:--","col_25":"|","col_28":"--:--","col_29":"--:--","col_30":"--:--","col_31":"","col_32":"","col_33":"","col_34":"","col_35":"","col_36":"","col_37":"","col_38":""},{"col_1":"","cheg":"--:--","saida":"--:--","col_4":"12:17","col_5":"--:--","col_6":"--:--","col_7":"|","col_10":"12:35","col_11":"--:--","col_12":"--:--","col_13":"|","col_16":"12:52","col_17":"--:--","col_18":"--:--","col_19":"|","col_22":"13:09","col_23":"--:--","col_24":"--:--","col_25":"|","col_28":"--:--","col_29":"--:--","col_30":"--:--","col_31":"","col_32":"","col_33":"","col_34":"","col_35":"","col_36":"","col_37":"","col_38":""},{"col_1":"","cheg":"--:--","saida":"--:--","col_4":"12:48","col_5":"13:03","col_6":"13:05","col_7":"|","col_10":"13:06","col_11":"13:21","col_12":"13:23","col_13":"|","col_16":"13:23","col_17":"13:38","col_18":"13:40","col_19":"|","col_22":"13:40","col_23":"13:55","col_24":"13:57","col_25":"|","col_28":"--:--","col_29":"--:--","col_30":"--:--","col_31":"","col_32":"","col_33":"","col_34":"","col_35":"","col_36":"","col_37":"","col_38":""},{"col_1":"","cheg":"--:--","saida":"--:--","col_4":"--:--","col_5":"13:10","col_6":"--:--","col_7":"|","col_10":"--:--","col_11":"13:28","col_12":"--:--","col_13":"|","col_16":"--:--","col_17":"13:45","col_18":"--:--","col_19":"|","col_22":"--:--","col_23":"14:02","col_24":"--:--","col_25":"|","col_28":"--:--","col_29":"--:--","col_30":"--:--","col_31":"","col_32":"","col_33":"","col_34":"","col_35":"","col_36":"","col_37":"","col_38":""},{"col_1":"","cheg":"--:--","saida":"--:--","col_4":"13:25","col_5":"--:--","col_6":"--:--","col_7":"|","col_10":"13:43","col_11":"--:--","col_12":"--:--","col_13":"|","col_16":"14:00","col_17":"--:--","col_18":"--:--","col_19":"|","col_22":"14:17","col_23":"--:--","col_24":"--:--","col_25":"|","col_28":"--:--","col_29":"--:--","col_30":"--:--","col_31":"","col_32":"","col_33":"","col_34":"","col_35":"","col_36":"","col_37":"","col_38":""},{"col_1":"","cheg":"--:--","saida":"--:--","col_4":"13:56","col_5":"14:11","col_6":"14:13","col_7":"|","col_10":"14:14","col_11":"14:29","col_12":"14:31","col_13":"|","col_16":"14:31","col_17":"14:46","col_18":"14:48","col_19":"|","col_22":"14:48","col_23":"15:03","col_24":"15:05","col_25":"|","col_28":"--:--","col_29":"--:--","col_30":"--:--","col_31":"","col_32":"","col_33":"","col_34":"","col_35":"","col_36":"","col_37":"","col_38":""},{"col_1":"","cheg":"T. Vivi Xavier","saida":"","col_4":"--:--","col_5":"14:18","col_6":"--:--","col_7":"|","col_10":"--:--","col_11":"14:36","col_12":"--:--","col_13":"|","col_16":"--:--","col_17":"14:53","col_18":"--:--","col_19":"|","col_22":"--:--","col_23":"15:10","col_24":"--:--","col_25":"|","col_28":"T. O. V.","col_29":"IFPR","col_30":"T. M. G","col_31":"","col_32":"","col_33":"","col_34":"","col_35":"","col_36":"","col_37":"","col_38":""},{"col_1":"","cheg":"Cheg.","saida":"Saída","col_4":"14:33","col_5":"--:--","col_6":"--:--","col_7":"|","col_10":"14:51","col_11":"--:--","col_12":"--:--","col_13":"|","col_16":"15:08","col_17":"--:--","col_18":"--:--","col_19":"|","col_22":"15:25","col_23":"--:--","col_24":"--:--","col_25":"|","col_28":"","col_29":"","col_30":"","col_31":"","col_32":"","col_33":"","col_34":"","col_35":"","col_36":"","col_37":"","col_38":""},{"col_1":"","cheg":"Carro do 803 tab. 15","saida":"","col_4":"15:04","col_5":"15:19","col_6":"15:21","col_7":"|","col_10":"15:22","col_11":"15:37","col_12":"15:39","col_13":"|","col_16":"15:39","col_17":"15:54","col_18":"15:56","col_19":"|","col_22":"15:56","col_23":"16:11","col_24":"16:13","col_25":"|","col_28":"","col_29":"","col_30":"","col_31":"","col_32":"","col_33":"","col_34":"","col_35":"","col_36":"","col_37":"","col_38":""},{"col_1":"","cheg":"--:--","saida":"--:--","col_4":"--:--","col_5":"15:26","col_6":"--:--","col_7":"|","col_10":"--:--","col_11":"15:44","col_12":"--:--","col_13":"|","col_16":"--:--","col_17":"16:01","col_18":"--:--","col_19":"|","col_22":"--:--","col_23":"16:18","col_24":"--:--","col_25":"|","col_28":"--:--","col_29":"18:00","col_30":"--:--","col_31":"","col_32":"","col_33":"","col_34":"","col_35":"","col_36":"","col_37":"","col_38":""},{"col_1":"","cheg":"--:--","saida":"--:--","col_4":"15:41","col_5":"--:--","col_6":"--:--","col_7":"|","col_10":"15:59","col_11":"--:--","col_12":"--:--","col_13":"|","col_16":"16:16","col_17":"--:--","col_18":"--:--","col_19":"|","col_22":"16:33","col_23":"--:--","col_24":"--:--","col_25":"|","col_28":"--:--","col_29":"--:--","col_30":"--:--","col_31":"","col_32":"","col_33":"","col_34":"","col_35":"","col_36":"","col_37":"","col_38":""},{"col_1":"","cheg":"--:--","saida":"--:--","col_4":"16:12","col_5":"16:27","col_6":"16:29","col_7":"|","col_10":"16:30","col_11":"16:45","col_12":"16:47","col_13":"|","col_16":"16:47","col_17":"17:02","col_18":"17:04","col_19":"|","col_22":"17:04","col_23":"17:19","col_24":"17:21","col_25":"|","col_28":"--:--","col_29":"18:05","col_30":"--:--","col_31":"","col_32":"","col_33":"","col_34":"","col_35":"","col_36":"","col_37":"","col_38":""},{"col_1":"","cheg":"--:--","saida":"--:--","col_4":"--:--","col_5":"16:34","col_6":"--:--","col_7":"|","col_10":"--:--","col_11":"16:52","col_12":"--:--","col_13":"|","col_16":"--:--","col_17":"17:09","col_18":"--:--","col_19":"|","col_22":"--:--","col_23":"17:26","col_24":"--:--","col_25":"|","col_28":"18:10","col_29":"--:--","col_30":"--:--","col_31":"","col_32":"","col_33":"","col_34":"","col_35":"","col_36":"","col_37":"","col_38":""},{"col_1":"","cheg":"Entra no 512 tab. 03","saida":"","col_4":"16:49","col_5":"--:--","col_6":"--:--","col_7":"|","col_10":"17:07","col_11":"--:--","col_12":"--:--","col_13":"|","col_16":"17:24","col_17":"--:--","col_18":"--:--","col_19":"|","col_22":"17:41","col_23":"--:--","col_24":"--:--","col_25":"|","col_28":"","col_29":"","col_30":"","col_31":"","col_32":"","col_33":"","col_34":"","col_35":"","col_36":"","col_37":"","col_38":""},{"col_1":"","cheg":"--:--","saida":"--:--","col_4":"17:21","col_5":"17:37","col_6":"17:39","col_7":"|","col_10":"17:40","col_11":"17:56","col_12":"17:58","col_13":"|","col_16":"--:--","col_17":"--:--","col_18":"--:--","col_19":"|","col_22":"--:--","col_23":"--:--","col_24":"--:--","col_25":"|","col_28":"--:--","col_29":"--:--","col_30":"--:--","col_31":"","col_32":"","col_33":"","col_34":"","col_35":"","col_36":"","col_37":"","col_38":""},{"col_1":"","cheg":"--:--","saida":"--:--","col_4":"--:--","col_5":"17:44","col_6":"--:--","col_7":"|","col_10":"--:--","col_11":"18:03","col_12":"--:--","col_13":"|","col_16":"17:59","col_17":"18:15","col_18":"18:17","col_19":"|","col_22":"18:18","col_23":"18:34","col_24":"18:36","col_25":"|","col_28":"--:--","col_29":"--:--","col_30":"--:--","col_31":"","col_32":"","col_33":"","col_34":"","col_35":"","col_36":"","col_37":"","col_38":""},{"col_1":"","cheg":"--:--","saida":"--:--","col_4":"18:00","col_5":"--:--","col_6":"--:--","col_7":"|","col_10":"18:19","col_11":"--:--","col_12":"--:--","col_13":"|","col_16":"--:--","col_17":"18:22","col_18":"--:--","col_19":"|","col_22":"--:--","col_23":"18:41","col_24":"--:--","col_25":"|","col_28":"--:--","col_29":"--:--","col_30":"--:--","col_31":"","col_32":"","col_33":"","col_34":"","col_35":"","col_36":"","col_37":"","col_38":""},{"col_1":"","cheg":"--:--","saida":"--:--","col_4":"18:37","col_5":"18:55","col_6":"18:58","col_7":"|","col_10":"18:56","col_11":"19:12","col_12":"19:14","col_13":"|","col_16":"18:38","col_17":"--:--","col_18":"--:--","col_19":"|","col_22":"18:57","col_23":"--:--","col_24":"--:--","col_25":"|","col_28":"--:--","col_29":"--:--","col_30":"--:--","col_31":"","col_32":"","col_33":"","col_34":"","col_35":"","col_36":"","col_37":"","col_38":""},{"col_1":"","cheg":"--:--","saida":"--:--","col_4":"--:--","col_5":"19:05","col_6":"--:--","col_7":"|","col_10":"--:--","col_11":"19:19","col_12":"--:--","col_13":"|","col_16":"19:15","col_17":"19:31","col_18":"19:33","col_19":"|","col_22":"--:--","col_23":"--:--","col_24":"--:--","col_25":"|","col_28":"--:--","col_29":"--:--","col_30":"--:--","col_31":"","col_32":"","col_33":"","col_34":"","col_35":"","col_36":"","col_37":"","col_38":""},{"col_1":"","cheg":"T. Vivi Xavier","saida":"","col_4":"19:24","col_5":"--:--","col_6":"--:--","col_7":"|","col_10":"19:35","col_11":"--:--","col_12":"--:--","col_13":"|","col_16":"--:--","col_17":"19:38","col_18":"--:--","col_19":"|","col_22":"19:38","col_23":"19:53","col_24":"19:55","col_25":"|","col_28":"T. O. V.","col_29":"IFPR","col_30":"T. M. G","col_31":"","col_32":"","col_33":"","col_34":"","col_35":"","col_36":"","col_37":"","col_38":""},{"col_1":"","cheg":"Cheg.","saida":"Saída","col_4":"20:01","col_5":"20:16","col_6":"20:18","col_7":"|","col_10":"--:--","col_11":"--:--","col_12":"--:--","col_13":"|","col_16":"19:53","col_17":"--:--","col_18":"--:--","col_19":"|","col_22":"--:--","col_23":"20:00","col_24":"--:--","col_25":"|","col_28":"","col_29":"","col_30":"","col_31":"","col_32":"","col_33":"","col_34":"","col_35":"","col_36":"","col_37":"","col_38":""},{"col_1":"","cheg":"Carro do 444 tab. 01","saida":"","col_4":"--:--","col_5":"20:23","col_6":"--:--","col_7":"|","col_10":"--:--","col_11":"--:--","col_12":"--:--","col_13":"|","col_16":"20:24","col_17":"20:39","col_18":"20:41","col_19":"|","col_22":"20:15","col_23":"--:--","col_24":"--:--","col_25":"|","col_28":"","col_29":"","col_30":"","col_31":"","col_32":"","col_33":"","col_34":"","col_35":"","col_36":"","col_37":"","col_38":""},{"col_1":"","cheg":"--:--","saida":"--:--","col_4":"20:38","col_5":"--:--","col_6":"--:--","col_7":"|","col_10":"--:--","col_11":"--:--","col_12":"--:--","col_13":"|","col_16":"--:--","col_17":"20:46","col_18":"--:--","col_19":"|","col_22":"20:47","col_23":"21:02","col_24":"21:04","col_25":"|","col_28":"--:--","col_29":"--:--","col_30":"22:33","col_31":"","col_32":"","col_33":"","col_34":"","col_35":"","col_36":"","col_37":"","col_38":""},{"col_1":"","cheg":"--:--","saida":"--:--","col_4":"21:10","col_5":"21:25","col_6":"21:27","col_7":"|","col_10":"--:--","col_11":"--:--","col_12":"--:--","col_13":"|","col_16":"21:01","col_17":"--:--","col_18":"--:--","col_19":"|","col_22":"--:--","col_23":"21:09","col_24":"--:--","col_25":"|","col_28":"--:--","col_29":"22:38","col_30":"--:--","col_31":"","col_32":"","col_33":"","col_34":"","col_35":"","col_36":"","col_37":"","col_38":""},{"col_1":"","cheg":"--:--","saida":"--:--","col_4":"--:--","col_5":"21:32","col_6":"--:--","col_7":"|","col_10":"--:--","col_11":"--:--","col_12":"--:--","col_13":"|","col_16":"21:33","col_17":"21:48","col_18":"21:50","col_19":"|","col_22":"21:24","col_23":"--:--","col_24":"--:--","col_25":"|","col_28":"22:45","col_29":"--:--","col_30":"--:--","col_31":"","col_32":"","col_33":"","col_34":"","col_35":"","col_36":"","col_37":"","col_38":""},{"col_1":"","cheg":"Entra no 512 tab. 03","saida":"","col_4":"21:47","col_5":"--:--","col_6":"--:--","col_7":"|","col_10":"--:--","col_11":"--:--","col_12":"--:--","col_13":"|","col_16":"--:--","col_17":"21:55","col_18":"--:--","col_19":"|","col_22":"21:56","col_23":"22:11","col_24":"22:13","col_25":"|","col_28":"","col_29":"","col_30":"","col_31":"","col_32":"","col_33":"","col_34":"","col_35":"","col_36":"","col_37":"","col_38":""},{"col_1":"","cheg":"--:--","saida":"--:--","col_4":"22:19","col_5":"22:34","col_6":"22:36","col_7":"|","col_10":"--:--","col_11":"--:--","col_12":"--:--","col_13":"|","col_16":"22:10","col_17":"--:--","col_18":"--:--","col_19":"|","col_22":"--:--","col_23":"22:18","col_24":"--:--","col_25":"|","col_28":"--:--","col_29":"--:--","col_30":"--:--","col_31":"","col_32":"","col_33":"","col_34":"","col_35":"","col_36":"","col_37":"","col_38":""},{"col_1":"","cheg":"--:--","saida":"--:--","col_4":"--:--","col_5":"22:41","col_6":"--:--","col_7":"|","col_10":"--:--","col_11":"--:--","col_12":"--:--","col_13":"|","col_16":"22:42","col_17":"22:57","col_18":"22:59","col_19":"|","col_22":"22:33","col_23":"--:--","col_24":"--:--","col_25":"|","col_28":"--:--","col_29":"--:--","col_30":"--:--","col_31":"","col_32":"","col_33":"","col_34":"","col_35":"","col_36":"","col_37":"","col_38":""},{"col_1":"","cheg":"T. Vivi Xavier","saida":"","col_4":"22:56","col_5":"--:--","col_6":"--:--","col_7":"|","col_10":"--:--","col_11":"--:--","col_12":"--:--","col_13":"|","col_16":"--:--","col_17":"23:04","col_18":"--:--","col_19":"|","col_22":"23:05","col_23":"23:20","col_24":"23:22","col_25":"|","col_28":"T. O. V.","col_29":"T. M. G","col_30":"N.Shop.","col_31":"","col_32":"","col_33":"","col_34":"","col_35":"","col_36":"","col_37":"","col_38":""},{"col_1":"","cheg":"Cheg.","saida":"Saída","col_4":"23:28","col_5":"23:43","col_6":"23:45","col_7":"|","col_10":"--:--","col_11":"--:--","col_12":"--:--","col_13":"|","col_16":"23:19","col_17":"--:--","col_18":"--:--","col_19":"|","col_22":"--:--","col_23":"23:27","col_24":"--:--","col_25":"|","col_28":"","col_29":"","col_30":"","col_31":"","col_32":"","col_33":"","col_34":"","col_35":"","col_36":"","col_37":"","col_38":""},{"col_1":"","cheg":"--:--","saida":"--:--","col_4":"--:--","col_5":"23:50","col_6":"--:--","col_7":"|","col_10":"--:--","col_11":"--:--","col_12":"--:--","col_13":"|","col_16":"23:51","col_17":"00:06","col_18":"--:--","col_19":"|","col_22":"23:42","col_23":"--:--","col_24":"--:--","col_25":"|","col_28":"--:--","col_29":"--:--","col_30":"--:--","col_31":"","col_32":"","col_33":"","col_34":"","col_35":"","col_36":"","col_37":"","col_38":""},{"col_1":"","cheg":"--:--","saida":"--:--","col_4":"00:05","col_5":"--:--","col_6":"--:--","col_7":"|","col_10":"--:--","col_11":"--:--","col_12":"--:--","col_13":"|","col_16":"--:--","col_17":"Rec.","col_18":"--:--","col_19":"|","col_22":"--:--","col_23":"--:--","col_24":"--:--","col_25":"|","col_28":"--:--","col_29":"--:--","col_30":"23:15","col_31":"","col_32":"","col_33":"","col_34":"","col_35":"","col_36":"","col_37":"","col_38":""},{"col_1":"","cheg":"--:--","saida":"--:--","col_4":"--:--","col_5":"--:--","col_6":"--:--","col_7":"|","col_10":"--:--","col_11":"--:--","col_12":"--:--","col_13":"|","col_16":"--:--","col_17":"--:--","col_18":"--:--","col_19":"|","col_22":"","col_23":"","col_24":"","col_25":"|","col_28":"--:--","col_29":"23:18","col_30":"--:--","col_31":"","col_32":"","col_33":"","col_34":"","col_35":"","col_36":"","col_37":"","col_38":""},{"col_1":"","cheg":"--:--","saida":"--:--","col_4":"--:--","col_5":"--:--","col_6":"--:--","col_7":"|","col_10":"--:--","col_11":"--:--","col_12":"--:--","col_13":"|","col_16":"--:--","col_17":"--:--","col_18":"--:--","col_19":"|","col_22":"--:--","col_23":"--:--","col_24":"--:--","col_25":"|","col_28":"23:33","col_29":"--:--","col_30":"--:--","col_31":"","col_32":"","col_33":"","col_34":"","col_35":"","col_36":"","col_37":"","col_38":""},{"col_1":"","cheg":"23:40","saida":"23:45","col_4":"--:--","col_5":"--:--","col_6":"--:--","col_7":"|","col_10":"--:--","col_11":"--:--","col_12":"--:--","col_13":"|","col_16":"--:--","col_17":"--:--","col_18":"--:--","col_19":"|","col_22":"--:--","col_23":"--:--","col_24":"--:--","col_25":"|","col_28":"--:--","col_29":"--:--","col_30":"--:--","col_31":"","col_32":"","col_33":"","col_34":"","col_35":"","col_36":"","col_37":"","col_38":""},{"col_1":"","cheg":"--:--","saida":"Rec.","col_4":"--:--","col_5":"--:--","col_6":"--:--","col_7":"|","col_10":"--:--","col_11":"--:--","col_12":"--:--","col_13":"|","col_16":"--:--","col_17":"--:--","col_18":"--:--","col_19":"|","col_22":"--:--","col_23":"--:--","col_24":"--:--","col_25":"|","col_28":"--:--","col_29":"--:--","col_30":"--:--","col_31":"","col_32":"","col_33":"","col_34":"","col_35":"","col_36":"","col_37":"","col_38":""},{"col_1":"","cheg":"Exclusivo shopping até às 23h","saida":"","col_4":"--:--","col_5":"--:--","col_6":"--:--","col_7":"|","col_10":"--:--","col_11":"--:--","col_12":"--:--","col_13":"|","col_16":"--:--","col_17":"--:--","col_18":"--:--","col_19":"|","col_22":"--:--","col_23":"--:--","col_24":"--:--","col_25":"|","col_28":"","col_29":"","col_30":"","col_31":"","col_32":"","col_33":"","col_34":"","col_35":"","col_36":"","col_37":"","col_38":""},{"col_1":"","cheg":"00:47","saida":"","col_4":"","col_5":"","col_6":"","col_7":"","col_10":"","col_11":"","col_12":"","col_13":"","col_16":"","col_17":"","col_18":"","col_19":"","col_22":"","col_23":"","col_24":"","col_25":"","col_28":"","col_29":"","col_30":"","col_31":"","col_32":"","col_33":"","col_34":"","col_35":"","col_36":"","col_37":"","col_38":""}],"id":"420-uteis"}