{"meta":{"linha":"913","dia_semana":"","data_execucao":"2026-06-23","titulo":"TABELA HORÁRIA","subtitulo":"","tipo":"sabado"},"colunas":[{"chave":"col_1","rotulo":"Coluna 1","largura":56,"alinhamento":"centro"},{"chave":"est_catuai","rotulo":"Est. Catuaí","largura":123,"alinhamento":"centro"},{"chave":"col_3","rotulo":"Coluna 3","largura":56,"alinhamento":"centro"},{"chave":"hosp_evange","rotulo":"Hosp. Evangé","largura":132,"alinhamento":"centro"},{"chave":"ernani","rotulo":"Ernani","largura":78,"alinhamento":"centro"},{"chave":"inicio","rotulo":"Inicio","largura":78,"alinhamento":"centro"},{"chave":"col_7","rotulo":"|","largura":56,"alinhamento":"centro"},{"chave":"est_catuai","rotulo":"Est. Catuaí","largura":123,"alinhamento":"centro"},{"chave":"col_9","rotulo":"Coluna 9","largura":56,"alinhamento":"centro"},{"chave":"hosp_evange","rotulo":"Hosp. Evangé","largura":132,"alinhamento":"centro"},{"chave":"ernani","rotulo":"Ernani","largura":78,"alinhamento":"centro"},{"chave":"inicio","rotulo":"Inicio","largura":78,"alinhamento":"centro"},{"chave":"col_13","rotulo":"|","largura":56,"alinhamento":"centro"},{"chave":"est_catuai","rotulo":"Est. Catuaí","largura":123,"alinhamento":"centro"},{"chave":"col_15","rotulo":"Coluna 15","largura":56,"alinhamento":"centro"},{"chave":"hosp_evange","rotulo":"Hosp. Evangé","largura":132,"alinhamento":"centro"},{"chave":"ernani","rotulo":"Ernani","largura":78,"alinhamento":"centro"},{"chave":"inicio","rotulo":"Inicio","largura":78,"alinhamento":"centro"},{"chave":"col_19","rotulo":"|","largura":56,"alinhamento":"centro"},{"chave":"est_catuai","rotulo":"Est. Catuaí","largura":123,"alinhamento":"centro"},{"chave":"col_21","rotulo":"Coluna 21","largura":56,"alinhamento":"centro"},{"chave":"hosp_evange","rotulo":"Hosp. Evangé","largura":132,"alinhamento":"centro"},{"chave":"ernani","rotulo":"Ernani","largura":78,"alinhamento":"centro"},{"chave":"inicio","rotulo":"Inicio","largura":78,"alinhamento":"centro"},{"chave":"col_25","rotulo":"|","largura":56,"alinhamento":"centro"},{"chave":"est_catuai","rotulo":"Est. Catuaí","largura":123,"alinhamento":"centro"},{"chave":"col_27","rotulo":"Coluna 27","largura":56,"alinhamento":"centro"},{"chave":"hosp_evange","rotulo":"Hosp. Evangé","largura":132,"alinhamento":"centro"},{"chave":"ernani","rotulo":"Ernani","largura":78,"alinhamento":"centro"},{"chave":"inicio","rotulo":"Inicio","largura":78,"alinhamento":"centro"},{"chave":"col_31","rotulo":"Coluna 31","largura":56,"alinhamento":"centro"},{"chave":"col_32","rotulo":"Coluna 32","largura":56,"alinhamento":"centro"}],"linhas":[{"col_1":"","est_catuai":"Cheg.","col_3":"Saída","hosp_evange":"","ernani":"","inicio":"","col_7":"|","col_9":"Saída","col_13":"|","col_15":"Saída","col_19":"|","col_21":"Saída","col_25":"|","col_27":"Saída","col_31":"","col_32":""},{"col_1":"","est_catuai":"Carro do 900 tab. 01","col_3":"--:--","hosp_evange":"","ernani":"","inicio":"","col_7":"|","col_9":"--:--","col_13":"|","col_15":"--:--","col_19":"|","col_21":"--:--","col_25":"|","col_27":"","col_31":"","col_32":""},{"col_1":"","est_catuai":"--:--","col_3":"--:--","hosp_evange":"--:--","ernani":"--:--","inicio":"06:59","col_7":"|","col_9":"--:--","col_13":"|","col_15":"--:--","col_19":"|","col_21":"--:--","col_25":"|","col_27":"--:--","col_31":"","col_32":""},{"col_1":"","est_catuai":"--:--","col_3":"--:--","hosp_evange":"--:--","ernani":"07:06","inicio":"--:--","col_7":"|","col_9":"--:--","col_13":"|","col_15":"--:--","col_19":"|","col_21":"--:--","col_25":"|","col_27":"--:--","col_31":"","col_32":""},{"col_1":"","est_catuai":"--:--","col_3":"--:--","hosp_evange":"07:33","ernani":"--:--","inicio":"--:--","col_7":"|","col_9":"--:--","col_13":"|","col_15":"--:--","col_19":"|","col_21":"--:--","col_25":"|","col_27":"--:--","col_31":"","col_32":""},{"col_1":"","est_catuai":"07:54","col_3":"06:39","hosp_evange":"08:19","ernani":"08:46","inicio":"--:--","col_7":"|","col_9":"06:59","col_13":"|","col_15":"07:19","col_19":"|","col_21":"07:39","col_25":"|","col_27":"07:59","col_31":"","col_32":""},{"col_1":"","est_catuai":"--:--","col_3":"--:--","hosp_evange":"09:13","ernani":"--:--","inicio":"--:--","col_7":"|","col_9":"--:--","col_13":"|","col_15":"--:--","col_19":"|","col_21":"--:--","col_25":"|","col_27":"--:--","col_31":"","col_32":""},{"col_1":"","est_catuai":"09:34","col_3":"08:19","hosp_evange":"--:--","ernani":"--:--","inicio":"--:--","col_7":"|","col_9":"08:39","col_13":"|","col_15":"08:59","col_19":"|","col_21":"09:12","col_25":"|","col_27":"--:--","col_31":"","col_32":""},{"col_1":"","est_catuai":"--:--","col_3":"--:--","hosp_evange":"10:05","ernani":"10:31","inicio":"--:--","col_7":"|","col_9":"--:--","col_13":"|","col_15":"Rec.","col_19":"|","col_21":"--:--","col_25":"|","col_27":"09:45","col_31":"","col_32":""},{"col_1":"","est_catuai":"--:--","col_3":"09:59","hosp_evange":"10:58","ernani":"--:--","inicio":"--:--","col_7":"|","col_9":"10:18","col_13":"|","col_15":"--:--","col_19":"|","col_21":"10:51","col_25":"|","col_27":"--:--","col_31":"","col_32":""},{"col_1":"","est_catuai":"11:19","col_3":"Rec.","hosp_evange":"11:44","ernani":"12:10","inicio":"--:--","col_7":"|","col_9":"--:--","col_13":"|","col_15":"--:--","col_19":"|","col_21":"--:--","col_25":"|","col_27":"11:24","col_31":"","col_32":""},{"col_1":"","est_catuai":"--:--","col_3":"--:--","hosp_evange":"12:37","ernani":"--:--","inicio":"--:--","col_7":"|","col_9":"11:57","col_13":"|","col_15":"--:--","col_19":"|","col_21":"12:30","col_25":"|","col_27":"--:--","col_31":"","col_32":""},{"col_1":"","est_catuai":"12:58","col_3":"--:--","hosp_evange":"13:23","ernani":"13:49","inicio":"--:--","col_7":"|","col_9":"--:--","col_13":"|","col_15":"--:--","col_19":"|","col_21":"--:--","col_25":"|","col_27":"13:03","col_31":"","col_32":""},{"col_1":"","est_catuai":"--:--","col_3":"--:--","hosp_evange":"14:16","ernani":"--:--","inicio":"--:--","col_7":"|","col_9":"13:36","col_13":"|","col_15":"--:--","col_19":"|","col_21":"14:09","col_25":"|","col_27":"--:--","col_31":"","col_32":""},{"col_1":"","est_catuai":"14:37","col_3":"--:--","hosp_evange":"15:02","ernani":"15:28","inicio":"--:--","col_7":"|","col_9":"--:--","col_13":"|","col_15":"--:--","col_19":"|","col_21":"--:--","col_25":"|","col_27":"14:42","col_31":"","col_32":""},{"col_1":"","est_catuai":"--:--","col_3":"--:--","hosp_evange":"15:55","ernani":"--:--","inicio":"--:--","col_7":"|","col_9":"15:15","col_13":"|","col_15":"--:--","col_19":"|","col_21":"15:48","col_25":"|","col_27":"--:--","col_31":"","col_32":""},{"col_1":"","est_catuai":"16:16","col_3":"--:--","hosp_evange":"16:41","ernani":"17:07","inicio":"--:--","col_7":"|","col_9":"--:--","col_13":"|","col_15":"--:--","col_19":"|","col_21":"--:--","col_25":"|","col_27":"16:21","col_31":"","col_32":""},{"col_1":"","est_catuai":"--:--","col_3":"--:--","hosp_evange":"17:34","ernani":"--:--","inicio":"--:--","col_7":"|","col_9":"16:54","col_13":"|","col_15":"--:--","col_19":"|","col_21":"17:27","col_25":"|","col_27":"--:--","col_31":"","col_32":""},{"col_1":"","est_catuai":"17:55","col_3":"--:--","hosp_evange":"18:20","ernani":"18:46","inicio":"--:--","col_7":"|","col_9":"--:--","col_13":"|","col_15":"--:--","col_19":"|","col_21":"--:--","col_25":"|","col_27":"18:00","col_31":"","col_32":""},{"col_1":"","est_catuai":"--:--","col_3":"--:--","hosp_evange":"19:13","ernani":"--:--","inicio":"--:--","col_7":"|","col_9":"18:33","col_13":"|","col_15":"--:--","col_19":"|","col_21":"19:06","col_25":"|","col_27":"--:--","col_31":"","col_32":""},{"col_1":"","est_catuai":"19:34","col_3":"--:--","hosp_evange":"19:59","ernani":"20:25","inicio":"--:--","col_7":"|","col_9":"--:--","col_13":"|","col_15":"--:--","col_19":"|","col_21":"--:--","col_25":"|","col_27":"19:39","col_31":"","col_32":""},{"col_1":"","est_catuai":"--:--","col_3":"--:--","hosp_evange":"20:52","ernani":"--:--","inicio":"Fim","col_7":"|","col_9":"20:12","col_13":"|","col_15":"--:--","col_19":"|","col_21":"20:45","col_25":"|","col_27":"--:--","col_31":"","col_32":""},{"col_1":"","est_catuai":"21:12","col_3":"--:--","hosp_evange":"21:37","ernani":"21:58","inicio":"22:03","col_7":"|","col_9":"--:--","col_13":"|","col_15":"--:--","col_19":"|","col_21":"--:--","col_25":"|","col_27":"21:17","col_31":"","col_32":""},{"col_1":"","est_catuai":"--:--","col_3":"--:--","hosp_evange":"--:--","ernani":"--:--","inicio":"Rec.","col_7":"|","col_9":"21:50","col_13":"|","col_15":"--:--","col_19":"|","col_21":"22:20","col_25":"|","col_27":"--:--","col_31":"","col_32":""},{"col_1":"","est_catuai":"--:--","col_3":"--:--","hosp_evange":"--:--","ernani":"--:--","inicio":"--:--","col_7":"|","col_9":"--:--","col_13":"|","col_15":"--:--","col_19":"|","col_21":"--:--","col_25":"|","col_27":"--:--","col_31":"","col_32":""},{"col_1":"","est_catuai":"--:--","col_3":"--:--","hosp_evange":"--:--","ernani":"--:--","inicio":"--:--","col_7":"|","col_9":"--:--","col_13":"|","col_15":"--:--","col_19":"|","col_21":"--:--","col_25":"|","col_27":"--:--","col_31":"","col_32":""},{"col_1":"","est_catuai":"15:04","col_3":"","hosp_evange":"","ernani":"","inicio":"","col_7":"","col_9":"","col_13":"","col_15":"","col_19":"","col_21":"","col_25":"","col_27":"","col_31":"","col_32":""},{"col_1":"","est_catuai":"","col_3":"913T","hosp_evange":"","ernani":"","inicio":"","col_7":"","col_9":"","col_13":"","col_15":"","col_19":"","col_21":"","col_25":"","col_27":"","col_31":"","col_32":""},{"col_1":"","est_catuai":"","col_3":"913L","hosp_evange":"","ernani":"","inicio":"","col_7":"","col_9":"","col_13":"","col_15":"","col_19":"","col_21":"","col_25":"","col_27":"","col_31":"","col_32":""}],"id":"913-sabado"}